{
  "orientation": "horizontal",
  "layout": "fullscreen",
  "slideDuration": 2,
  "animation": "slide",
  "bgColor": "#000000",
  "sections": [
    {
      "slideDirection": "top",
      "slideDuration": 5
    },
    {
      "slideDirection": "right",
      "slideDuration": 5
    },
    {
      "slideDirection": "bottom",
      "slideDuration": 5
    }
  ],
  "ticker": {
    "text": "welcome to nextview 43444444",
    "color": "#fcfcfc",
    "bgColor": "#010e0e",
    "speed": 12,
    "fontSize": 57,
    "position": "top"
  }
}